README.md
setup.cfg
setup.py
distributions/Binomialdistribution.py
distributions/Gaussiandistribution.py
distributions/Generaldistribution.py
distributions/__init__.py
shyam_test.egg-info/PKG-INFO
shyam_test.egg-info/SOURCES.txt
shyam_test.egg-info/dependency_links.txt
shyam_test.egg-info/not-zip-safe
shyam_test.egg-info/top_level.txt